xrdconfig/__init__.py
xrdconfig/cli.py
xrdconfig/py.typed
xrdconfig-0.2.0.dist-info/entry_points.txt
xrdconfig-0.2.0.dist-info/WHEEL
xrdconfig-0.2.0.dist-info/METADATA
xrdconfig-0.2.0.dist-info/RECORD
