Metadata-Version: 2.1
Name: xrdconfig
Version: 0.2.0
Summary: Easy access to Xrootd config parameters
Author-email: Luke Kreczko <kreczko@cern.ch>
Requires-Python: >=3.8
Classifier: Development Status :: 1 - Planning
Classifier: Intended Audience :: Science/Research
Classifier: Intended Audience :: Developers
Classifier: License :: OSI Approved :: Apache Software License
Classifier: Operating System :: OS Independent
Classifier: Programming Language :: Python
Classifier: Programming Language :: Python :: 3
Classifier: Programming Language :: Python :: 3 :: Only
Classifier: Programming Language :: Python :: 3.8
Classifier: Programming Language :: Python :: 3.9
Classifier: Programming Language :: Python :: 3.10
Classifier: Topic :: Scientific/Engineering
Classifier: Typing :: Typed
Requires-Dist: plumbum
Requires-Dist: typer >=0.4.0
Requires-Dist: pytest >=6 ; extra == "dev"
Requires-Dist: pytest-cov >=3 ; extra == "dev"
Requires-Dist: Sphinx>=4.0 ; extra == "docs"
Requires-Dist: myst_parser>=0.13 ; extra == "docs"
Requires-Dist: sphinx-book-theme>=0.1.0 ; extra == "docs"
Requires-Dist: sphinx_copybutton ; extra == "docs"
Requires-Dist: pytest >=6 ; extra == "test"
Requires-Dist: pytest-cov >=3 ; extra == "test"
Project-URL: Bug Tracker, https://github.com/uobdic/xrdconfig/issues
Project-URL: Changelog, https://github.com/uobdic/xrdconfig/releases
Project-URL: Discussions, https://github.com/uobdic/xrdconfig/discussions
Project-URL: Homepage, https://github.com/uobdic/xrdconfig
Provides-Extra: dev
Provides-Extra: docs
Provides-Extra: test
